bookbot/__init__.py
bookbot/_dir.md
bookbot/book/__init__.py
bookbot/book/_dir.md
bookbot/bot/__init__.py
bookbot/bot/_dir.md
bookbot/bot/parse/__init__.py
bookbot/bot/parse/_dir.md
bookbot/bot/request/__init__.py
bookbot/bot/request/_dir.md
bookbot/cli/__init__.py
bookbot/cli/_dir.md
bookbot/gui/__init__.py
bookbot/gui/_dir.md
bookbot/storage/__init__.py
bookbot/storage/_dir.md
bookbot-1.0.dev2.dist-info/METADATA
bookbot-1.0.dev2.dist-info/WHEEL
bookbot-1.0.dev2.dist-info/entry_points.txt
bookbot-1.0.dev2.dist-info/licenses/LICENSE
bookbot-1.0.dev2.dist-info/RECORD
